stocksnake/__init__.py
stocksnake/_stocksnake.so
stocksnake-0.0.1.dist-info/LICENSE.md
stocksnake-0.0.1.dist-info/METADATA
stocksnake-0.0.1.dist-info/WHEEL
stocksnake-0.0.1.dist-info/top_level.txt
stocksnake-0.0.1.dist-info/RECORD
