Metadata-Version: 2.1
Name: stocksnake
Version: 0.0.1
Summary: Simple stockfish wrapper, 100 times faster than pychess + includes great board evaluation function.
Home-page: UNKNOWN
Author: Piotr Dabkowski
Author-email: piodrus@gmail.com
License: UNKNOWN
Platform: UNKNOWN
